musicxml_to_pcs/__init__.py
musicxml_to_pcs/cli.py
musicxml_to_pcs/extractor.py
musicxml_to_pcs-0.1.0.dist-info/METADATA
musicxml_to_pcs-0.1.0.dist-info/WHEEL
musicxml_to_pcs-0.1.0.dist-info/entry_points.txt
musicxml_to_pcs-0.1.0.dist-info/licenses/LICENSE
musicxml_to_pcs-0.1.0.dist-info/RECORD
