Metadata-Version: 2.4
Name: musicxml-to-pcs
Version: 0.1.0
Summary: Extract pitch class sets and interval vectors from MusicXML files, segmented by chord symbols
Project-URL: Homepage, https://github.com/flatnine/musicxml-to-pcs
Project-URL: Repository, https://github.com/flatnine/musicxml-to-pcs
Project-URL: Issues, https://github.com/flatnine/musicxml-to-pcs/issues
Author-email: Mike Rubini <mike@flatnine.co>
License: MIT
License-File: LICENSE
Keywords: computational-musicology,forte-class,interval-vector,jazz,music,music-analysis,music-theory,musicxml,pitch-class-set
Classifier: Development Status :: 4 - Beta
Classifier: Intended Audience :: Developers
Classifier: Intended Audience :: Science/Research
Classifier: License :: OSI Approved :: MIT License
Classifier: Operating System :: OS Independent
Classifier: Programming Language :: Python :: 3
Classifier: Programming Language :: Python :: 3.9
Classifier: Programming Language :: Python :: 3.10
Classifier: Programming Language :: Python :: 3.11
Classifier: Programming Language :: Python :: 3.12
Classifier: Topic :: Multimedia :: Sound/Audio :: Analysis
Classifier: Topic :: Scientific/Engineering :: Information Analysis
Requires-Python: >=3.9
Requires-Dist: music21>=9.1.0
Provides-Extra: dev
Requires-Dist: pytest-cov>=4.0.0; extra == 'dev'
Requires-Dist: pytest>=7.0.0; extra == 'dev'
